cerebrixos_auth/__init__.py
cerebrixos_auth/config.py
cerebrixos_auth/jwks.py
cerebrixos_auth/test_tokens.py
cerebrixos_auth/verifier.py
cerebrixos_auth/contracts/base.py
cerebrixos_auth-0.2.1.dist-info/METADATA
cerebrixos_auth-0.2.1.dist-info/WHEEL
cerebrixos_auth-0.2.1.dist-info/top_level.txt
cerebrixos_auth-0.2.1.dist-info/RECORD
