Metadata-Version: 2.4
Name: cerebrixos-auth
Version: 0.2.1
Summary: CerebrixOS OIDC/JWT auth helpers (test + prod)
Author-email: CerebrixOS <dev@cerebrixos.com>
Requires-Python: >=3.9
Requires-Dist: requests>=2.31
Requires-Dist: python-jose[cryptography]>=3.3.0
